chatshell/__init__.py
chatshell/chatshell_core.py
chatshell/chatshell_server.py
chatshell/context_manager.py
chatshell/llm_server.py
chatshell/utils_rag.py
chatshell/vectorstore.py
chatshell_python-0.3.0.dist-info/licenses/LICENSE
chatshell_python-0.3.0.dist-info/METADATA
chatshell_python-0.3.0.dist-info/WHEEL
chatshell_python-0.3.0.dist-info/entry_points.txt
chatshell_python-0.3.0.dist-info/top_level.txt
chatshell_python-0.3.0.dist-info/RECORD
