Metadata-Version: 2.4
Name: chatshell-python
Version: 0.3.0
Summary: Chatshell - An interactive in-chat shell for LLM-based tasks.
Author-email: Julian Schweigert <julianschweigert@gmail.com>
License:                     GNU AFFERO GENERAL PUBLIC LICENSE
Project-URL: Homepage, https://github.com/jschw/chatshell
Project-URL: Repository, https://github.com/jschw/chatshell
Project-URL: Issues, https://github.com/jschw/chatshell/issues
Requires-Python: >=3.8
License-File: LICENSE
Requires-Dist: appdirs
Requires-Dist: beautifulsoup4
Requires-Dist: fastapi
Requires-Dist: hnswlib
Requires-Dist: llama-cpp-python[server]
Requires-Dist: langchain
Requires-Dist: langchain-classic
Requires-Dist: langchain-community
Requires-Dist: langchain-core
Requires-Dist: langchain-text-splitters
Requires-Dist: light-embed
Requires-Dist: markdownify
Requires-Dist: networkx
Requires-Dist: nltk
Requires-Dist: numpy
Requires-Dist: openai
Requires-Dist: PyPDF2
Requires-Dist: pyperclip
Requires-Dist: regex
Requires-Dist: requests
Requires-Dist: sse-starlette
Requires-Dist: scikit-learn
Dynamic: license-file
